TrakoDracoPy.cpython-310-darwin.so
TrakoDracoPy-0.0.13b3.dev9.data/data/bin/draco_decoder
TrakoDracoPy-0.0.13b3.dev9.data/data/bin/draco_encoder
TrakoDracoPy-0.0.13b3.dev9.data/data/include/draco/draco_features.h
TrakoDracoPy-0.0.13b3.dev9.data/data/include/draco/animation/keyframe_animation.h
TrakoDracoPy-0.0.13b3.dev9.data/data/include/draco/animation/keyframe_animation_decoder.h
TrakoDracoPy-0.0.13b3.dev9.data/data/include/draco/animation/keyframe_animation_encoder.h
TrakoDracoPy-0.0.13b3.dev9.data/data/include/draco/attributes/attribute_octahedron_transform.h
TrakoDracoPy-0.0.13b3.dev9.data/data/include/draco/attributes/attribute_quantization_transform.h
TrakoDracoPy-0.0.13b3.dev9.data/data/include/draco/attributes/attribute_transform.h
TrakoDracoPy-0.0.13b3.dev9.data/data/include/draco/attributes/attribute_transform_data.h
TrakoDracoPy-0.0.13b3.dev9.data/data/include/draco/attributes/attribute_transform_type.h
TrakoDracoPy-0.0.13b3.dev9.data/data/include/draco/attributes/geometry_attribute.h
TrakoDracoPy-0.0.13b3.dev9.data/data/include/draco/attributes/geometry_indices.h
TrakoDracoPy-0.0.13b3.dev9.data/data/include/draco/attributes/point_attribute.h
TrakoDracoPy-0.0.13b3.dev9.data/data/include/draco/compression/decode.h
TrakoDracoPy-0.0.13b3.dev9.data/data/include/draco/compression/encode.h
TrakoDracoPy-0.0.13b3.dev9.data/data/include/draco/compression/encode_base.h
TrakoDracoPy-0.0.13b3.dev9.data/data/include/draco/compression/expert_encode.h
TrakoDracoPy-0.0.13b3.dev9.data/data/include/draco/compression/attributes/attributes_decoder.h
TrakoDracoPy-0.0.13b3.dev9.data/data/include/draco/compression/attributes/attributes_decoder_interface.h
TrakoDracoPy-0.0.13b3.dev9.data/data/include/draco/compression/attributes/attributes_encoder.h
TrakoDracoPy-0.0.13b3.dev9.data/data/include/draco/compression/attributes/kd_tree_attributes_decoder.h
TrakoDracoPy-0.0.13b3.dev9.data/data/include/draco/compression/attributes/kd_tree_attributes_encoder.h
TrakoDracoPy-0.0.13b3.dev9.dist-info/LICENSE
TrakoDracoPy-0.0.13b3.dev9.dist-info/METADATA
TrakoDracoPy-0.0.13b3.dev9.dist-info/WHEEL
TrakoDracoPy-0.0.13b3.dev9.dist-info/top_level.txt
TrakoDracoPy-0.0.13b3.dev9.dist-info/RECORD
